gallerycrawler/__init__.py
gallerycrawler/cli.py
gallerycrawler/crawler.py
gallerycrawler/exporter.py
gallerycrawler/page_details.py
gallerycrawler/toolbox.py
gallerycrawler/utils.py
gallerycrawler-0.1.0.dist-info/AUTHORS
gallerycrawler-0.1.0.dist-info/LICENSE
gallerycrawler-0.1.0.dist-info/METADATA
gallerycrawler-0.1.0.dist-info/WHEEL
gallerycrawler-0.1.0.dist-info/entry_points.txt
gallerycrawler-0.1.0.dist-info/top_level.txt
gallerycrawler-0.1.0.dist-info/RECORD
